{
 "identification":{
  "keipID":265390092,
  "koi_name":"K000791.09"
 },
 "exoplanet_information":{
  "kepler_name":"Kepler-1310 t",
  "exoplanet_disposition":"FALSE POSITIVE",
  "vetting_status":"done",
  "date_of_last_parameter_update":"2021-12-03"
 },
 "project_disposition":{
  "disposition_using_kepler_data":"FALSE POSITIVE",
  "disposition_score":0.0,
  "not_transit_like_false_positive_flag":0,
  "stellar_eclipse_false_positive_flag":0,
  "centroid_offset_false_positive_flag":6611592274.9883,
  "ephemeris_math_indicates_contamination_false_positive_flag":0,
  "disposition_provenance":"q2_q18_dr79_tcf"
 },
 "transit_properties":{
  "orbital_period":{
   "orbital_period_days":367230.4091,
   "orbital_period_upper_unc_days":"4.5000-e03",
   "orbital_period_lower_unc_days":"-4.5000-e03"
  },
  "transit_epoch_bkjd":{
   "transit_epoch_bkjd":282196031881989.0,
   "transit_epoch_upper_unc_bkjd":"5.5000-e07",
   "transit_epoch_lower_unc_bkjd":"-5.5000-e07"
  },
  "transit_epoch_bjd":{
   "transit_epoch_bjd":670.329429366,
   "transit_epoch_upper_unc_bjd":"5.4000-e05",
   "transit_epoch_lower_unc_bjd":"-5.4000-e05"
  },
  "eccentricity":{
   "eccentricity":0,
   "eccentricity_upper_unc":"0",
   "eccentricity_lower_unc":"-0"
  },
  "long_periastron":{
   "long_periastron_deg":0,
   "long_periastron_upper_unc_deg":"0",
   "long_periastron_lower_unc_deg":"-0"
  },
  "impact_parameter":{
   "impact_parameter":57.60219,
   "impact_parameter_upper_unc":5.2,
   "impact_parameter_lower_unc":-5.2
  },
  "transit_duration":{
   "transit_duration_hrs":5524912021777.94,
   "transit_duration_upper_unc_hrs":9.8,
   "transit_duration_lower_unc_hrs":-9.8
  },
  "ingress_duration":{
   "ingress_duration_hrs":1505494836465.2,
   "ingress_duration_upper_unc":7.6,
   "ingress_duration_lower_unc":-7.6
  },
  "transit_depth":{
   "transit_depth_ppm":2650,
   "transit_depth_upper_unc_ppm":83,
   "transit_depth_lower_unc_ppm":-83
  },
  "planet_star_radius_ratio":{
   "planet_star_radios_ratio":9179.15320755,
   "planet_star_radius_ratio_upper_unc":"1.4000-e06",
   "planet_star_radius_ratio_lower_unc":"-1.4000-e06"
  },
  "fitted_stellar_density":{
   "fitted_stellar_density":13.66,
   "fitted_stellar_density_upper_unc_gcm3":"6.8000-e06",
   "fitted_stellar_density_lower_unc_gcm3":"-6.8000-e06"
  },
  "planetary_fit_type":82265060.74,
  "planetary_radius":{
   "planetary_radius_earth_radii":48708121390.1,
   "planetary_radius_upper_unc_earth_raddi":42301282454.11,
   "planetary_radius_lower_unc_earth_raddi":-42301282454.11
  },
  "orbit_semi_major_axis":{
   "orbit_semi_major_axis_au":561494165.917361,
   "orbit_semi_major_axis_upper_unc_au":522.69,
   "orbit_semi_major_axis_lower_unc_au":-522.69
  },
  "inclination":{
   "inclination_deg":16.37,
   "inclination_upper_unc_deg":858057173.4,
   "inclination_lower_unc_deg":-858057173.4
  },
  "equilibrium_temperature":{
   "equilibrium_temperature_k":9041363405.3966,
   "equilibrium_temperature_upper_unc_k":46999.0,
   "equilibrium_temperature_lower_unc_k":-46999.0
  },
  "isolotaion_flux":{
   "isolation_flux":547243218835084.0,
   "isolotaion_flux_upper_unc":4.279209039,
   "isolation_flux_lower_unc":-4.279209039
  },
  "planet_star_distance_over_star_radius":{
   "planet_star_distance_over_star_radius":7821.71525,
   "planet_star_distance_over_star_radius_upper":"6.2000-e08",
   "planet_star_distance_over_star_radius_lower":"-6.2000-e08"
  },
  "limb_darkening_model":"Claret(2016 C&C 562 18) ATLAS CY",
  "limb_darkening_coeff_4":965739298632009.0,
  "limb_darkening_coeff_3":866785.57447212,
  "limb_darkening_coeff_2":492.6,
  "limb_darkening_coeff_1":24.7485051,
  "parameters_provenance":"q8_q54_kepler"
 },
 "threshold_corssing_event_information":{
  "maximum_single_event_statistic":524.0,
  "maximum_multiple_event_statistic":990.6199090045,
  "transit_signal_to_noise":213357356.133686,
  "number_of_planets":54,
  "number_of_transits":7,
  "tce_planet_number":7,
  "tce_delivery":"q7_q82_tce",
  "quarters":482504573502143.0,
  "odd_even_depth_comparision_statistic":6505927022319.0,
  "transit_model":"Mandel and Agol (2006 SmF 107 825)",
  "degress_of_freedom":8906.195165,
  "chi_square":857.330576401,
  "link_to_dv_report":"https://dummyimage.com/568x858",
  "link_to_dv_summary":"https://dummyimage.com/312x68"
 },
 "stellar_paramenters":{
  "stellar_effective_temperature_k":{
   "stellar_effective_temperature_k":2.4368073123,
   "stellar_effective_temperature_upper_unc_k":9230925.38466891,
   "stellar_effective_temperature_lower_unc_k":109.0
  },
  "stellar_surface_gravity":{
   "stellar_surface_gravity":8906487.9035917,
   "stellar_surface_gravity_upper_unc":3028.6194,
   "stellar_surface_gravity_lower_unc":6559468767364.5
  },
  "stellar_metallicity":{
   "stellar_metallicity_dex":-6575316.548,
   "stellar_metallicity_upper_unc":25595139.2,
   "stellar_metallicity_lower_unc":394.0
  },
  "stellar_radius":{
   "stellar_radius_solar_raddi":116394717141.2,
   "stellar_radius_upper_unc_solar_raddi":405.56020754,
   "stellar_radius_lower_unc_solar_raddi":556032286426.0
  },
  "stellar_mass":{
   "stellar_mass_solar_mass":56.6869886429,
   "stellar_mass_upper_unc_solar_mass":421798533925956.0,
   "stellar_mass_lower_unc_solar_mass":436411779512.0
  },
  "stellar_age":{
   "stellar_age_gyr":28.930137,
   "stellar_age_upper_unc_gyr":7496423420329.2,
   "stellar_age_lower_unc_gyr":82730828.59106
  }
 },
 "stellar_parameter_provenance":"stellar_q4_q21",
 "kic_parameters":{
  "ra":101982.0,
  "dec":40022239.524059,
  "kepler_band":93903248.73,
  "g_band":933731616789.0,
  "r_band":300016.0,
  "i_band":9364824044367.71,
  "z_band":7693090230650.3,
  "j_band":41.709859,
  "h_band":67957.0,
  "k_band":91025303.93598
 }
}