{
 "identification":{
  "keipID":723206243,
  "koi_name":"K000312.04"
 },
 "exoplanet_information":{
  "kepler_name":"Kepler-167 a",
  "exoplanet_disposition":"FALSE POSITIVE",
  "vetting_status":"done",
  "date_of_last_parameter_update":"2020-02-04"
 },
 "project_disposition":{
  "disposition_using_kepler_data":"NOT DISPOSITIONED",
  "disposition_score":4.0,
  "not_transit_like_false_positive_flag":0,
  "stellar_eclipse_false_positive_flag":0,
  "centroid_offset_false_positive_flag":269.54998478,
  "ephemeris_math_indicates_contamination_false_positive_flag":0,
  "disposition_provenance":"q3_q50_dr51_tcs"
 },
 "transit_properties":{
  "orbital_period":{
   "orbital_period_days":8930802947759.5,
   "orbital_period_upper_unc_days":"1.7000-e07",
   "orbital_period_lower_unc_days":"-1.7000-e07"
  },
  "transit_epoch_bkjd":{
   "transit_epoch_bkjd":82296.296,
   "transit_epoch_upper_unc_bkjd":"2.7000-e02",
   "transit_epoch_lower_unc_bkjd":"-2.7000-e02"
  },
  "transit_epoch_bjd":{
   "transit_epoch_bjd":85394445.638,
   "transit_epoch_upper_unc_bjd":"4.6000-e04",
   "transit_epoch_lower_unc_bjd":"-4.6000-e04"
  },
  "eccentricity":{
   "eccentricity":1,
   "eccentricity_upper_unc":"0",
   "eccentricity_lower_unc":"-0"
  },
  "long_periastron":{
   "long_periastron_deg":1,
   "long_periastron_upper_unc_deg":"0",
   "long_periastron_lower_unc_deg":"-0"
  },
  "impact_parameter":{
   "impact_parameter":8.88132,
   "impact_parameter_upper_unc":7.9,
   "impact_parameter_lower_unc":-7.9
  },
  "transit_duration":{
   "transit_duration_hrs":915379879470.718,
   "transit_duration_upper_unc_hrs":8.9,
   "transit_duration_lower_unc_hrs":-8.9
  },
  "ingress_duration":{
   "ingress_duration_hrs":239548040.5,
   "ingress_duration_upper_unc":5.6,
   "ingress_duration_lower_unc":-5.6
  },
  "transit_depth":{
   "transit_depth_ppm":7116,
   "transit_depth_upper_unc_ppm":75,
   "transit_depth_lower_unc_ppm":-75
  },
  "planet_star_radius_ratio":{
   "planet_star_radios_ratio":517.88,
   "planet_star_radius_ratio_upper_unc":"4.6000-e07",
   "planet_star_radius_ratio_lower_unc":"-4.6000-e07"
  },
  "fitted_stellar_density":{
   "fitted_stellar_density":216.55,
   "fitted_stellar_density_upper_unc_gcm3":"2.6000-e04",
   "fitted_stellar_density_lower_unc_gcm3":"-2.6000-e04"
  },
  "planetary_fit_type":18.9112682539619,
  "planetary_radius":{
   "planetary_radius_earth_radii":5126.705470085,
   "planetary_radius_upper_unc_earth_raddi":30266836081706.4,
   "planetary_radius_lower_unc_earth_raddi":-30266836081706.4
  },
  "orbit_semi_major_axis":{
   "orbit_semi_major_axis_au":143629473.726,
   "orbit_semi_major_axis_upper_unc_au":80083.7549666277,
   "orbit_semi_major_axis_lower_unc_au":-80083.7549666277
  },
  "inclination":{
   "inclination_deg":8368991118439.9,
   "inclination_upper_unc_deg":175738365616589.0,
   "inclination_lower_unc_deg":-175738365616589.0
  },
  "equilibrium_temperature":{
   "equilibrium_temperature_k":15.57129986,
   "equilibrium_temperature_upper_unc_k":500074068791981.0,
   "equilibrium_temperature_lower_unc_k":-500074068791981.0
  },
  "isolotaion_flux":{
   "isolation_flux":49067.634,
   "isolotaion_flux_upper_unc":1.0,
   "isolation_flux_lower_unc":-1.0
  },
  "planet_star_distance_over_star_radius":{
   "planet_star_distance_over_star_radius":449.0,
   "planet_star_distance_over_star_radius_upper":"4.7000-e04",
   "planet_star_distance_over_star_radius_lower":"-4.7000-e04"
  },
  "limb_darkening_model":"Claret(2021 C&Q 585 59) ATLAS IM",
  "limb_darkening_coeff_4":2779727.0,
  "limb_darkening_coeff_3":41509507.55,
  "limb_darkening_coeff_2":6.448157735477,
  "limb_darkening_coeff_1":8734.569031831,
  "parameters_provenance":"q7_q34_koi"
 },
 "threshold_corssing_event_information":{
  "maximum_single_event_statistic":237160670939.25,
  "maximum_multiple_event_statistic":1568858.11779097,
  "transit_signal_to_noise":95613385330.89,
  "number_of_planets":50,
  "number_of_transits":10,
  "tce_planet_number":4,
  "tce_delivery":"q2_q24_tce",
  "quarters":347507807239.4,
  "odd_even_depth_comparision_statistic":8.0,
  "transit_model":"Mandel and Agol (2012 RoP 762 783)",
  "degress_of_freedom":27081.309922,
  "chi_square":48396081081225.3,
  "link_to_dv_report":"https://www.lorempixel.com/176/744",
  "link_to_dv_summary":"https://placeimg.com/314/266/any"
 },
 "stellar_paramenters":{
  "stellar_effective_temperature_k":{
   "stellar_effective_temperature_k":79358304.564,
   "stellar_effective_temperature_upper_unc_k":2457434029.6574,
   "stellar_effective_temperature_lower_unc_k":40095.0
  },
  "stellar_surface_gravity":{
   "stellar_surface_gravity":50885844514.6,
   "stellar_surface_gravity_upper_unc":7290764712130.4,
   "stellar_surface_gravity_lower_unc":21918906185.59
  },
  "stellar_metallicity":{
   "stellar_metallicity_dex":-6013191921.7035,
   "stellar_metallicity_upper_unc":-43444019.94,
   "stellar_metallicity_lower_unc":201184828322.587
  },
  "stellar_radius":{
   "stellar_radius_solar_raddi":59.182290010836,
   "stellar_radius_upper_unc_solar_raddi":0.2237148,
   "stellar_radius_lower_unc_solar_raddi":372620628675.4
  },
  "stellar_mass":{
   "stellar_mass_solar_mass":241779869263754.0,
   "stellar_mass_upper_unc_solar_mass":32805.0,
   "stellar_mass_lower_unc_solar_mass":0.0
  },
  "stellar_age":{
   "stellar_age_gyr":7107983567007.69,
   "stellar_age_upper_unc_gyr":4.11759725,
   "stellar_age_lower_unc_gyr":593077.56634
  }
 },
 "stellar_parameter_provenance":"stellar_q6_q16",
 "kic_parameters":{
  "ra":29571748.18,
  "dec":95347081919861.4,
  "kepler_band":22656701.4925106,
  "g_band":54060563.8,
  "r_band":337276.560047,
  "i_band":63931.84,
  "z_band":80881549.1,
  "j_band":92004.6299,
  "h_band":1051097461439.67,
  "k_band":63923.0
 }
}