{
 "identification":{
  "keipID":843476978,
  "koi_name":"K000945.02"
 },
 "exoplanet_information":{
  "kepler_name":"Kepler-1579 t",
  "exoplanet_disposition":"FALSE POSITIVE",
  "vetting_status":"done",
  "date_of_last_parameter_update":"2020-01-11"
 },
 "project_disposition":{
  "disposition_using_kepler_data":"NOT DISPOSITIONED",
  "disposition_score":2.0,
  "not_transit_like_false_positive_flag":1,
  "stellar_eclipse_false_positive_flag":1,
  "centroid_offset_false_positive_flag":41913.2711336,
  "ephemeris_math_indicates_contamination_false_positive_flag":1,
  "disposition_provenance":"q2_q70_dr28_tcb"
 },
 "transit_properties":{
  "orbital_period":{
   "orbital_period_days":5000.7471169956,
   "orbital_period_upper_unc_days":"1.1000-e01",
   "orbital_period_lower_unc_days":"-1.1000-e01"
  },
  "transit_epoch_bkjd":{
   "transit_epoch_bkjd":2586625090.963,
   "transit_epoch_upper_unc_bkjd":"6.4000-e04",
   "transit_epoch_lower_unc_bkjd":"-6.4000-e04"
  },
  "transit_epoch_bjd":{
   "transit_epoch_bjd":35618496049.9987,
   "transit_epoch_upper_unc_bjd":"5.1000-e04",
   "transit_epoch_lower_unc_bjd":"-5.1000-e04"
  },
  "eccentricity":{
   "eccentricity":0,
   "eccentricity_upper_unc":"1",
   "eccentricity_lower_unc":"-1"
  },
  "long_periastron":{
   "long_periastron_deg":0,
   "long_periastron_upper_unc_deg":"1",
   "long_periastron_lower_unc_deg":"-1"
  },
  "impact_parameter":{
   "impact_parameter":8.4,
   "impact_parameter_upper_unc":8.3,
   "impact_parameter_lower_unc":-8.3
  },
  "transit_duration":{
   "transit_duration_hrs":5.1,
   "transit_duration_upper_unc_hrs":9.7,
   "transit_duration_lower_unc_hrs":-9.7
  },
  "ingress_duration":{
   "ingress_duration_hrs":3876213439.0,
   "ingress_duration_upper_unc":6.4,
   "ingress_duration_lower_unc":-6.4
  },
  "transit_depth":{
   "transit_depth_ppm":9951,
   "transit_depth_upper_unc_ppm":58,
   "transit_depth_lower_unc_ppm":-58
  },
  "planet_star_radius_ratio":{
   "planet_star_radios_ratio":542.53203768495,
   "planet_star_radius_ratio_upper_unc":"8.5000-e01",
   "planet_star_radius_ratio_lower_unc":"-8.5000-e01"
  },
  "fitted_stellar_density":{
   "fitted_stellar_density":3413.97219,
   "fitted_stellar_density_upper_unc_gcm3":"6.3000-e03",
   "fitted_stellar_density_lower_unc_gcm3":"-6.3000-e03"
  },
  "planetary_fit_type":749966253.20681,
  "planetary_radius":{
   "planetary_radius_earth_radii":3.46,
   "planetary_radius_upper_unc_earth_raddi":44.3912559935252,
   "planetary_radius_lower_unc_earth_raddi":-44.3912559935252
  },
  "orbit_semi_major_axis":{
   "orbit_semi_major_axis_au":9.1,
   "orbit_semi_major_axis_upper_unc_au":3747.32,
   "orbit_semi_major_axis_lower_unc_au":-3747.32
  },
  "inclination":{
   "inclination_deg":2906.55150322,
   "inclination_upper_unc_deg":4592870429.2,
   "inclination_lower_unc_deg":-4592870429.2
  },
  "equilibrium_temperature":{
   "equilibrium_temperature_k":153436975356016.0,
   "equilibrium_temperature_upper_unc_k":1616879061260.4,
   "equilibrium_temperature_lower_unc_k":-1616879061260.4
  },
  "isolotaion_flux":{
   "isolation_flux":629442355852954.0,
   "isolotaion_flux_upper_unc":311314684512.8,
   "isolation_flux_lower_unc":-311314684512.8
  },
  "planet_star_distance_over_star_radius":{
   "planet_star_distance_over_star_radius":9739.1340377,
   "planet_star_distance_over_star_radius_upper":"6.4000-e07",
   "planet_star_distance_over_star_radius_lower":"-6.4000-e07"
  },
  "limb_darkening_model":"Claret(2016 Q&C 687 16) ATLAS QB",
  "limb_darkening_coeff_4":42548350699.2,
  "limb_darkening_coeff_3":90802213034904.0,
  "limb_darkening_coeff_2":32207.5174988395,
  "limb_darkening_coeff_1":97037014407461.0,
  "parameters_provenance":"q6_q28_kepler"
 },
 "threshold_corssing_event_information":{
  "maximum_single_event_statistic":9965.49178,
  "maximum_multiple_event_statistic":13712.496,
  "transit_signal_to_noise":2905850001.0,
  "number_of_planets":41,
  "number_of_transits":5,
  "tce_planet_number":1,
  "tce_delivery":"q5_q34_tce",
  "quarters":850938748.2,
  "odd_even_depth_comparision_statistic":47.8,
  "transit_model":"Mandel and Agol (2003 SeG 514 195)",
  "degress_of_freedom":84159144141148.7,
  "chi_square":52209527670172.7,
  "link_to_dv_report":"https://dummyimage.com/117x136",
  "link_to_dv_summary":"https://placekitten.com/388/915"
 },
 "stellar_paramenters":{
  "stellar_effective_temperature_k":{
   "stellar_effective_temperature_k":847466516.38,
   "stellar_effective_temperature_upper_unc_k":353019602728.0,
   "stellar_effective_temperature_lower_unc_k":5242.0
  },
  "stellar_surface_gravity":{
   "stellar_surface_gravity":77527006.403,
   "stellar_surface_gravity_upper_unc":15.4,
   "stellar_surface_gravity_lower_unc":2721571.16677
  },
  "stellar_metallicity":{
   "stellar_metallicity_dex":-599875874052152.0,
   "stellar_metallicity_upper_unc":3967.8,
   "stellar_metallicity_lower_unc":-2198972424.638
  },
  "stellar_radius":{
   "stellar_radius_solar_raddi":676004265509.39,
   "stellar_radius_upper_unc_solar_raddi":9179171503.29,
   "stellar_radius_lower_unc_solar_raddi":54672468025.2
  },
  "stellar_mass":{
   "stellar_mass_solar_mass":0.34246912971975,
   "stellar_mass_upper_unc_solar_mass":636414937352.67,
   "stellar_mass_lower_unc_solar_mass":63.36
  },
  "stellar_age":{
   "stellar_age_gyr":6576.6443180366,
   "stellar_age_upper_unc_gyr":1921047.52,
   "stellar_age_lower_unc_gyr":709.4663537001
  }
 },
 "stellar_parameter_provenance":"stellar_q3_q35",
 "kic_parameters":{
  "ra":8133018.41,
  "dec":1275113.48386286,
  "kepler_band":448602.899887,
  "g_band":1801254251984.5,
  "r_band":790365407152684.0,
  "i_band":3.9108037873,
  "z_band":54719.63557538,
  "j_band":85073529.4652,
  "h_band":52153700586.0,
  "k_band":27399575601693.0
 }
}