{
 "identification":{
  "keipID":782375707,
  "koi_name":"K000719.02"
 },
 "exoplanet_information":{
  "kepler_name":"Kepler-699 t",
  "exoplanet_disposition":"FALSE POSITIVE",
  "vetting_status":"done",
  "date_of_last_parameter_update":"2021-01-01"
 },
 "project_disposition":{
  "disposition_using_kepler_data":"NOT DISPOSITIONED",
  "disposition_score":0.0,
  "not_transit_like_false_positive_flag":1,
  "stellar_eclipse_false_positive_flag":1,
  "centroid_offset_false_positive_flag":13.288,
  "ephemeris_math_indicates_contamination_false_positive_flag":1,
  "disposition_provenance":"q8_q12_dr45_tce"
 },
 "transit_properties":{
  "orbital_period":{
   "orbital_period_days":3975732.56,
   "orbital_period_upper_unc_days":"5.7000-e01",
   "orbital_period_lower_unc_days":"-5.7000-e01"
  },
  "transit_epoch_bkjd":{
   "transit_epoch_bkjd":4925512827190.89,
   "transit_epoch_upper_unc_bkjd":"8.9000-e04",
   "transit_epoch_lower_unc_bkjd":"-8.9000-e04"
  },
  "transit_epoch_bjd":{
   "transit_epoch_bjd":682868.295,
   "transit_epoch_upper_unc_bjd":"9.5000-e04",
   "transit_epoch_lower_unc_bjd":"-9.5000-e04"
  },
  "eccentricity":{
   "eccentricity":1,
   "eccentricity_upper_unc":"0",
   "eccentricity_lower_unc":"-0"
  },
  "long_periastron":{
   "long_periastron_deg":1,
   "long_periastron_upper_unc_deg":"0",
   "long_periastron_lower_unc_deg":"-0"
  },
  "impact_parameter":{
   "impact_parameter":53137995085091.0,
   "impact_parameter_upper_unc":8.8,
   "impact_parameter_lower_unc":-8.8
  },
  "transit_duration":{
   "transit_duration_hrs":50128.0,
   "transit_duration_upper_unc_hrs":6.0,
   "transit_duration_lower_unc_hrs":-6.0
  },
  "ingress_duration":{
   "ingress_duration_hrs":78835479923.1,
   "ingress_duration_upper_unc":0.2,
   "ingress_duration_lower_unc":-0.2
  },
  "transit_depth":{
   "transit_depth_ppm":8097,
   "transit_depth_upper_unc_ppm":38,
   "transit_depth_lower_unc_ppm":-38
  },
  "planet_star_radius_ratio":{
   "planet_star_radios_ratio":691320644063.0,
   "planet_star_radius_ratio_upper_unc":"2.6000-e07",
   "planet_star_radius_ratio_lower_unc":"-2.6000-e07"
  },
  "fitted_stellar_density":{
   "fitted_stellar_density":581572.819724087,
   "fitted_stellar_density_upper_unc_gcm3":"6.2000-e09",
   "fitted_stellar_density_lower_unc_gcm3":"-6.2000-e09"
  },
  "planetary_fit_type":622.1371157,
  "planetary_radius":{
   "planetary_radius_earth_radii":43048319847800.6,
   "planetary_radius_upper_unc_earth_raddi":559395.0,
   "planetary_radius_lower_unc_earth_raddi":-559395.0
  },
  "orbit_semi_major_axis":{
   "orbit_semi_major_axis_au":5420882.62992,
   "orbit_semi_major_axis_upper_unc_au":1724.8,
   "orbit_semi_major_axis_lower_unc_au":-1724.8
  },
  "inclination":{
   "inclination_deg":808.37386,
   "inclination_upper_unc_deg":906615936.55,
   "inclination_lower_unc_deg":-906615936.55
  },
  "equilibrium_temperature":{
   "equilibrium_temperature_k":195415898415479.0,
   "equilibrium_temperature_upper_unc_k":9670925.3,
   "equilibrium_temperature_lower_unc_k":-9670925.3
  },
  "isolotaion_flux":{
   "isolation_flux":844.475035587,
   "isolotaion_flux_upper_unc":877439901.8458,
   "isolation_flux_lower_unc":-877439901.8458
  },
  "planet_star_distance_over_star_radius":{
   "planet_star_distance_over_star_radius":844527.89388,
   "planet_star_distance_over_star_radius_upper":"5.3000-e05",
   "planet_star_distance_over_star_radius_lower":"-5.3000-e05"
  },
  "limb_darkening_model":"Claret(2019 A&D 195 83) ATLAS RH",
  "limb_darkening_coeff_4":388054317844.9,
  "limb_darkening_coeff_3":23195926.776,
  "limb_darkening_coeff_2":5650.2861481,
  "limb_darkening_coeff_1":7540846820746.4,
  "parameters_provenance":"q6_q70_kepler"
 },
 "threshold_corssing_event_information":{
  "maximum_single_event_statistic":7431035.64619316,
  "maximum_multiple_event_statistic":566845.261110914,
  "transit_signal_to_noise":68812189.2493,
  "number_of_planets":81,
  "number_of_transits":10,
  "tce_planet_number":5,
  "tce_delivery":"q6_q76_tce",
  "quarters":59.0,
  "odd_even_depth_comparision_statistic":4.62529771876885,
  "transit_model":"Mandel and Agol (2017 LeC 872 674)",
  "degress_of_freedom":78625752.4477113,
  "chi_square":58625275.823,
  "link_to_dv_report":"https://placeimg.com/42/449/any",
  "link_to_dv_summary":"https://placeimg.com/500/1017/any"
 },
 "stellar_paramenters":{
  "stellar_effective_temperature_k":{
   "stellar_effective_temperature_k":69448938224207.0,
   "stellar_effective_temperature_upper_unc_k":50330668449.95,
   "stellar_effective_temperature_lower_unc_k":851592758369820.0
  },
  "stellar_surface_gravity":{
   "stellar_surface_gravity":76.978823,
   "stellar_surface_gravity_upper_unc":67853.797311486,
   "stellar_surface_gravity_lower_unc":766.3121
  },
  "stellar_metallicity":{
   "stellar_metallicity_dex":8015202059435.0,
   "stellar_metallicity_upper_unc":578121343.18,
   "stellar_metallicity_lower_unc":7925.1084
  },
  "stellar_radius":{
   "stellar_radius_solar_raddi":1367.7664403,
   "stellar_radius_upper_unc_solar_raddi":0.823098,
   "stellar_radius_lower_unc_solar_raddi":87350979616884.0
  },
  "stellar_mass":{
   "stellar_mass_solar_mass":707391839889645.0,
   "stellar_mass_upper_unc_solar_mass":370309312258.283,
   "stellar_mass_lower_unc_solar_mass":585285900581.782
  },
  "stellar_age":{
   "stellar_age_gyr":154407.250275,
   "stellar_age_upper_unc_gyr":2.0,
   "stellar_age_lower_unc_gyr":2728221.82231
  }
 },
 "stellar_parameter_provenance":"stellar_q4_q30",
 "kic_parameters":{
  "ra":1243312468.4814,
  "dec":320758730.99,
  "kepler_band":6612800379.61,
  "g_band":5475587956.45262,
  "r_band":428775.4454287,
  "i_band":371.968663,
  "z_band":1.33212,
  "j_band":364.92642,
  "h_band":127940651543912.0,
  "k_band":368349.22515
 }
}