{
 "identification":{
  "keipID":207859869,
  "koi_name":"K000651.05"
 },
 "exoplanet_information":{
  "kepler_name":"Kepler-1421 b",
  "exoplanet_disposition":"FALSE POSITIVE",
  "vetting_status":"done",
  "date_of_last_parameter_update":"2020-06-06"
 },
 "project_disposition":{
  "disposition_using_kepler_data":"FALSE POSITIVE",
  "disposition_score":8.0,
  "not_transit_like_false_positive_flag":0,
  "stellar_eclipse_false_positive_flag":0,
  "centroid_offset_false_positive_flag":807674012541958.0,
  "ephemeris_math_indicates_contamination_false_positive_flag":0,
  "disposition_provenance":"q4_q70_dr36_tcs"
 },
 "transit_properties":{
  "orbital_period":{
   "orbital_period_days":8.63,
   "orbital_period_upper_unc_days":"4.7000-e09",
   "orbital_period_lower_unc_days":"-4.7000-e09"
  },
  "transit_epoch_bkjd":{
   "transit_epoch_bkjd":690507593168.0,
   "transit_epoch_upper_unc_bkjd":"2.8000-e01",
   "transit_epoch_lower_unc_bkjd":"-2.8000-e01"
  },
  "transit_epoch_bjd":{
   "transit_epoch_bjd":4797245459.0,
   "transit_epoch_upper_unc_bjd":"3.8000-e05",
   "transit_epoch_lower_unc_bjd":"-3.8000-e05"
  },
  "eccentricity":{
   "eccentricity":1,
   "eccentricity_upper_unc":"0",
   "eccentricity_lower_unc":"-0"
  },
  "long_periastron":{
   "long_periastron_deg":1,
   "long_periastron_upper_unc_deg":"0",
   "long_periastron_lower_unc_deg":"-0"
  },
  "impact_parameter":{
   "impact_parameter":2895.84,
   "impact_parameter_upper_unc":5.2,
   "impact_parameter_lower_unc":-5.2
  },
  "transit_duration":{
   "transit_duration_hrs":92.19426270727,
   "transit_duration_upper_unc_hrs":8.7,
   "transit_duration_lower_unc_hrs":-8.7
  },
  "ingress_duration":{
   "ingress_duration_hrs":662.1363,
   "ingress_duration_upper_unc":3.5,
   "ingress_duration_lower_unc":-3.5
  },
  "transit_depth":{
   "transit_depth_ppm":6070,
   "transit_depth_upper_unc_ppm":58,
   "transit_depth_lower_unc_ppm":-58
  },
  "planet_star_radius_ratio":{
   "planet_star_radios_ratio":779.604,
   "planet_star_radius_ratio_upper_unc":"1.7000-e01",
   "planet_star_radius_ratio_lower_unc":"-1.7000-e01"
  },
  "fitted_stellar_density":{
   "fitted_stellar_density":3207427826.7,
   "fitted_stellar_density_upper_unc_gcm3":"4.8000-e02",
   "fitted_stellar_density_lower_unc_gcm3":"-4.8000-e02"
  },
  "planetary_fit_type":81458856.78,
  "planetary_radius":{
   "planetary_radius_earth_radii":631.594,
   "planetary_radius_upper_unc_earth_raddi":3033726592.428,
   "planetary_radius_lower_unc_earth_raddi":-3033726592.428
  },
  "orbit_semi_major_axis":{
   "orbit_semi_major_axis_au":6548.520252582,
   "orbit_semi_major_axis_upper_unc_au":45906441588.783,
   "orbit_semi_major_axis_lower_unc_au":-45906441588.783
  },
  "inclination":{
   "inclination_deg":15.75,
   "inclination_upper_unc_deg":5158692035.4346,
   "inclination_lower_unc_deg":-5158692035.4346
  },
  "equilibrium_temperature":{
   "equilibrium_temperature_k":53.59682422,
   "equilibrium_temperature_upper_unc_k":990353099440635.0,
   "equilibrium_temperature_lower_unc_k":-990353099440635.0
  },
  "isolotaion_flux":{
   "isolation_flux":514113.3352,
   "isolotaion_flux_upper_unc":1924391126219.0,
   "isolation_flux_lower_unc":-1924391126219.0
  },
  "planet_star_distance_over_star_radius":{
   "planet_star_distance_over_star_radius":184449051.2,
   "planet_star_distance_over_star_radius_upper":"9.7000-e04",
   "planet_star_distance_over_star_radius_lower":"-9.7000-e04"
  },
  "limb_darkening_model":"Claret(2016 B&A 825 54) ATLAS AR",
  "limb_darkening_coeff_4":26041950.7927,
  "limb_darkening_coeff_3":59585584639440.0,
  "limb_darkening_coeff_2":77358591.197,
  "limb_darkening_coeff_1":2096005351367.0,
  "parameters_provenance":"q3_q36_koi"
 },
 "threshold_corssing_event_information":{
  "maximum_single_event_statistic":95.71008868,
  "maximum_multiple_event_statistic":52909.9369775,
  "transit_signal_to_noise":436097.5553963,
  "number_of_planets":60,
  "number_of_transits":4,
  "tce_planet_number":7,
  "tce_delivery":"q2_q70_tce",
  "quarters":9509142432.31,
  "odd_even_depth_comparision_statistic":66276000430002.0,
  "transit_model":"Mandel and Agol (2009 EaG 834 385)",
  "degress_of_freedom":361567156189459.0,
  "chi_square":60294459.43646,
  "link_to_dv_report":"https://www.lorempixel.com/77/411",
  "link_to_dv_summary":"https://placeimg.com/286/351/any"
 },
 "stellar_paramenters":{
  "stellar_effective_temperature_k":{
   "stellar_effective_temperature_k":85365052651598.3,
   "stellar_effective_temperature_upper_unc_k":97397034489786.5,
   "stellar_effective_temperature_lower_unc_k":789451117.0
  },
  "stellar_surface_gravity":{
   "stellar_surface_gravity":35980759.5019,
   "stellar_surface_gravity_upper_unc":4151119.0,
   "stellar_surface_gravity_lower_unc":5913713925.7525
  },
  "stellar_metallicity":{
   "stellar_metallicity_dex":-9222307572.43,
   "stellar_metallicity_upper_unc":58086106765418.5,
   "stellar_metallicity_lower_unc":6174001090.11
  },
  "stellar_radius":{
   "stellar_radius_solar_raddi":60948740122571.0,
   "stellar_radius_upper_unc_solar_raddi":417404414.235,
   "stellar_radius_lower_unc_solar_raddi":8065182.2757284
  },
  "stellar_mass":{
   "stellar_mass_solar_mass":2743260.21,
   "stellar_mass_upper_unc_solar_mass":51.6026,
   "stellar_mass_lower_unc_solar_mass":8641135732777.0
  },
  "stellar_age":{
   "stellar_age_gyr":9304253077124.98,
   "stellar_age_upper_unc_gyr":556530.86583,
   "stellar_age_lower_unc_gyr":5908965.48
  }
 },
 "stellar_parameter_provenance":"stellar_q7_q44",
 "kic_parameters":{
  "ra":6835.454,
  "dec":74086718613.76,
  "kepler_band":7772357930441.0,
  "g_band":46652576718005.0,
  "r_band":3729541465149.0,
  "i_band":568.10725,
  "z_band":836.6946057,
  "j_band":56104458671.0,
  "h_band":7.18466097296,
  "k_band":617992.9494494
 }
}