{
 "identification":{
  "keipID":508767970,
  "koi_name":"K000560.01"
 },
 "exoplanet_information":{
  "kepler_name":"Kepler-274 m",
  "exoplanet_disposition":"FALSE POSITIVE",
  "vetting_status":"done",
  "date_of_last_parameter_update":"2021-01-23"
 },
 "project_disposition":{
  "disposition_using_kepler_data":"NOT DISPOSITIONED",
  "disposition_score":1.0,
  "not_transit_like_false_positive_flag":1,
  "stellar_eclipse_false_positive_flag":0,
  "centroid_offset_false_positive_flag":324849378273605.0,
  "ephemeris_math_indicates_contamination_false_positive_flag":0,
  "disposition_provenance":"q2_q66_dr61_tcd"
 },
 "transit_properties":{
  "orbital_period":{
   "orbital_period_days":9503090175.0,
   "orbital_period_upper_unc_days":"5.4000-e08",
   "orbital_period_lower_unc_days":"-5.4000-e08"
  },
  "transit_epoch_bkjd":{
   "transit_epoch_bkjd":8305557009.0,
   "transit_epoch_upper_unc_bkjd":"5.7000-e07",
   "transit_epoch_lower_unc_bkjd":"-5.7000-e07"
  },
  "transit_epoch_bjd":{
   "transit_epoch_bjd":46786.58988,
   "transit_epoch_upper_unc_bjd":"9.6000-e07",
   "transit_epoch_lower_unc_bjd":"-9.6000-e07"
  },
  "eccentricity":{
   "eccentricity":1,
   "eccentricity_upper_unc":"0",
   "eccentricity_lower_unc":"-0"
  },
  "long_periastron":{
   "long_periastron_deg":1,
   "long_periastron_upper_unc_deg":"0",
   "long_periastron_lower_unc_deg":"-0"
  },
  "impact_parameter":{
   "impact_parameter":564880506203951.0,
   "impact_parameter_upper_unc":2.4,
   "impact_parameter_lower_unc":-2.4
  },
  "transit_duration":{
   "transit_duration_hrs":8673023.416715,
   "transit_duration_upper_unc_hrs":7.4,
   "transit_duration_lower_unc_hrs":-7.4
  },
  "ingress_duration":{
   "ingress_duration_hrs":7559984379892.38,
   "ingress_duration_upper_unc":4.8,
   "ingress_duration_lower_unc":-4.8
  },
  "transit_depth":{
   "transit_depth_ppm":4283,
   "transit_depth_upper_unc_ppm":18,
   "transit_depth_lower_unc_ppm":-18
  },
  "planet_star_radius_ratio":{
   "planet_star_radios_ratio":645266435853.0,
   "planet_star_radius_ratio_upper_unc":"5.6000-e01",
   "planet_star_radius_ratio_lower_unc":"-5.6000-e01"
  },
  "fitted_stellar_density":{
   "fitted_stellar_density":736528199.9772,
   "fitted_stellar_density_upper_unc_gcm3":"5.9000-e08",
   "fitted_stellar_density_lower_unc_gcm3":"-5.9000-e08"
  },
  "planetary_fit_type":7790.262,
  "planetary_radius":{
   "planetary_radius_earth_radii":552623556322.8,
   "planetary_radius_upper_unc_earth_raddi":3.474559164,
   "planetary_radius_lower_unc_earth_raddi":-3.474559164
  },
  "orbit_semi_major_axis":{
   "orbit_semi_major_axis_au":2711859.243,
   "orbit_semi_major_axis_upper_unc_au":250015026.98958,
   "orbit_semi_major_axis_lower_unc_au":-250015026.98958
  },
  "inclination":{
   "inclination_deg":1583563.3734,
   "inclination_upper_unc_deg":91132970.802166,
   "inclination_lower_unc_deg":-91132970.802166
  },
  "equilibrium_temperature":{
   "equilibrium_temperature_k":74677436049.8,
   "equilibrium_temperature_upper_unc_k":7478515289585.77,
   "equilibrium_temperature_lower_unc_k":-7478515289585.77
  },
  "isolotaion_flux":{
   "isolation_flux":87200462282.9,
   "isolotaion_flux_upper_unc":0.0,
   "isolation_flux_lower_unc":-0.0
  },
  "planet_star_distance_over_star_radius":{
   "planet_star_distance_over_star_radius":6572923267.6,
   "planet_star_distance_over_star_radius_upper":"6.6000-e07",
   "planet_star_distance_over_star_radius_lower":"-6.6000-e07"
  },
  "limb_darkening_model":"Claret(2009 Q&P 940 95) ATLAS DC",
  "limb_darkening_coeff_4":8.5,
  "limb_darkening_coeff_3":14315589.76,
  "limb_darkening_coeff_2":81244.923752257,
  "limb_darkening_coeff_1":743460735937615.0,
  "parameters_provenance":"q6_q29_koi"
 },
 "threshold_corssing_event_information":{
  "maximum_single_event_statistic":25462297.636667,
  "maximum_multiple_event_statistic":3.479503406,
  "transit_signal_to_noise":702933143.8864,
  "number_of_planets":3,
  "number_of_transits":2,
  "tce_planet_number":5,
  "tce_delivery":"q4_q60_tce",
  "quarters":25980558537.81,
  "odd_even_depth_comparision_statistic":66707505377.87,
  "transit_model":"Mandel and Agol (2020 StS 111 390)",
  "degress_of_freedom":978719293722.0,
  "chi_square":661887.585,
  "link_to_dv_report":"https://dummyimage.com/809x477",
  "link_to_dv_summary":"https://placeimg.com/5/351/any"
 },
 "stellar_paramenters":{
  "stellar_effective_temperature_k":{
   "stellar_effective_temperature_k":52334408555470.6,
   "stellar_effective_temperature_upper_unc_k":601143783084.58,
   "stellar_effective_temperature_lower_unc_k":996815344125062.0
  },
  "stellar_surface_gravity":{
   "stellar_surface_gravity":785099811.33365,
   "stellar_surface_gravity_upper_unc":3155781.1921133,
   "stellar_surface_gravity_lower_unc":4247.1261515
  },
  "stellar_metallicity":{
   "stellar_metallicity_dex":-423987050.6006,
   "stellar_metallicity_upper_unc":-984.9986824346,
   "stellar_metallicity_lower_unc":9010112293.737
  },
  "stellar_radius":{
   "stellar_radius_solar_raddi":69288851.849478,
   "stellar_radius_upper_unc_solar_raddi":373.191512,
   "stellar_radius_lower_unc_solar_raddi":33588442881171.0
  },
  "stellar_mass":{
   "stellar_mass_solar_mass":206292093224.87,
   "stellar_mass_upper_unc_solar_mass":2.262307511,
   "stellar_mass_lower_unc_solar_mass":66.0
  },
  "stellar_age":{
   "stellar_age_gyr":67607204782.0,
   "stellar_age_upper_unc_gyr":8939.4,
   "stellar_age_lower_unc_gyr":3777336417.98
  }
 },
 "stellar_parameter_provenance":"stellar_q6_q83",
 "kic_parameters":{
  "ra":807743.28,
  "dec":356986750898.3,
  "kepler_band":258.0,
  "g_band":17.9,
  "r_band":74161339726001.5,
  "i_band":736534.823,
  "z_band":1229246716913.0,
  "j_band":0.608,
  "h_band":37026963.5514,
  "k_band":7064.5514513
 }
}