{
 "identification":{
  "keipID":402826312,
  "koi_name":"K000465.08"
 },
 "exoplanet_information":{
  "kepler_name":"Kepler-476 k",
  "exoplanet_disposition":"FALSE POSITIVE",
  "vetting_status":"done",
  "date_of_last_parameter_update":"2020-09-01"
 },
 "project_disposition":{
  "disposition_using_kepler_data":"FALSE POSITIVE",
  "disposition_score":2.0,
  "not_transit_like_false_positive_flag":1,
  "stellar_eclipse_false_positive_flag":0,
  "centroid_offset_false_positive_flag":630399793.1,
  "ephemeris_math_indicates_contamination_false_positive_flag":1,
  "disposition_provenance":"q6_q47_dr65_tco"
 },
 "transit_properties":{
  "orbital_period":{
   "orbital_period_days":3589.631484,
   "orbital_period_upper_unc_days":"3.3000-e08",
   "orbital_period_lower_unc_days":"-3.3000-e08"
  },
  "transit_epoch_bkjd":{
   "transit_epoch_bkjd":91542983381130.0,
   "transit_epoch_upper_unc_bkjd":"9.6000-e03",
   "transit_epoch_lower_unc_bkjd":"-9.6000-e03"
  },
  "transit_epoch_bjd":{
   "transit_epoch_bjd":28660.2351392445,
   "transit_epoch_upper_unc_bjd":"1.9000-e04",
   "transit_epoch_lower_unc_bjd":"-1.9000-e04"
  },
  "eccentricity":{
   "eccentricity":0,
   "eccentricity_upper_unc":"1",
   "eccentricity_lower_unc":"-1"
  },
  "long_periastron":{
   "long_periastron_deg":0,
   "long_periastron_upper_unc_deg":"1",
   "long_periastron_lower_unc_deg":"-1"
  },
  "impact_parameter":{
   "impact_parameter":33200.54,
   "impact_parameter_upper_unc":5.8,
   "impact_parameter_lower_unc":-5.8
  },
  "transit_duration":{
   "transit_duration_hrs":914302.3,
   "transit_duration_upper_unc_hrs":1.8,
   "transit_duration_lower_unc_hrs":-1.8
  },
  "ingress_duration":{
   "ingress_duration_hrs":7009808.9117964,
   "ingress_duration_upper_unc":2.3,
   "ingress_duration_lower_unc":-2.3
  },
  "transit_depth":{
   "transit_depth_ppm":4559,
   "transit_depth_upper_unc_ppm":42,
   "transit_depth_lower_unc_ppm":-42
  },
  "planet_star_radius_ratio":{
   "planet_star_radios_ratio":309979.5153818,
   "planet_star_radius_ratio_upper_unc":"5.4000-e07",
   "planet_star_radius_ratio_lower_unc":"-5.4000-e07"
  },
  "fitted_stellar_density":{
   "fitted_stellar_density":7988062.11,
   "fitted_stellar_density_upper_unc_gcm3":"7.1000-e08",
   "fitted_stellar_density_lower_unc_gcm3":"-7.1000-e08"
  },
  "planetary_fit_type":7443.6,
  "planetary_radius":{
   "planetary_radius_earth_radii":949.10961294,
   "planetary_radius_upper_unc_earth_raddi":97822597257.8613,
   "planetary_radius_lower_unc_earth_raddi":-97822597257.8613
  },
  "orbit_semi_major_axis":{
   "orbit_semi_major_axis_au":3590.145143563,
   "orbit_semi_major_axis_upper_unc_au":68356571.487425,
   "orbit_semi_major_axis_lower_unc_au":-68356571.487425
  },
  "inclination":{
   "inclination_deg":794198886.1,
   "inclination_upper_unc_deg":734393312954.878,
   "inclination_lower_unc_deg":-734393312954.878
  },
  "equilibrium_temperature":{
   "equilibrium_temperature_k":491.457,
   "equilibrium_temperature_upper_unc_k":770077552108.0,
   "equilibrium_temperature_lower_unc_k":-770077552108.0
  },
  "isolotaion_flux":{
   "isolation_flux":104731.73025673,
   "isolotaion_flux_upper_unc":7675622118521.7,
   "isolation_flux_lower_unc":-7675622118521.7
  },
  "planet_star_distance_over_star_radius":{
   "planet_star_distance_over_star_radius":5.439427,
   "planet_star_distance_over_star_radius_upper":"4.4000-e04",
   "planet_star_distance_over_star_radius_lower":"-4.4000-e04"
  },
  "limb_darkening_model":"Claret(2013 D&C 552 75) ATLAS HA",
  "limb_darkening_coeff_4":86270710792977.0,
  "limb_darkening_coeff_3":8373275407993.0,
  "limb_darkening_coeff_2":8.39954526027,
  "limb_darkening_coeff_1":88449647.45,
  "parameters_provenance":"q7_q51_kepler"
 },
 "threshold_corssing_event_information":{
  "maximum_single_event_statistic":1663970074.7,
  "maximum_multiple_event_statistic":532758823.18,
  "transit_signal_to_noise":8379281.61,
  "number_of_planets":59,
  "number_of_transits":10,
  "tce_planet_number":3,
  "tce_delivery":"q4_q89_tce",
  "quarters":6539027.61,
  "odd_even_depth_comparision_statistic":5054285.615,
  "transit_model":"Mandel and Agol (2011 FpB 468 863)",
  "degress_of_freedom":683684.54,
  "chi_square":4434491.12575,
  "link_to_dv_report":"https://placeimg.com/874/299/any",
  "link_to_dv_summary":"https://placeimg.com/411/859/any"
 },
 "stellar_paramenters":{
  "stellar_effective_temperature_k":{
   "stellar_effective_temperature_k":617177034382963.0,
   "stellar_effective_temperature_upper_unc_k":878.554,
   "stellar_effective_temperature_lower_unc_k":159008341.66
  },
  "stellar_surface_gravity":{
   "stellar_surface_gravity":53433497.32,
   "stellar_surface_gravity_upper_unc":7595690.0,
   "stellar_surface_gravity_lower_unc":77265.65394
  },
  "stellar_metallicity":{
   "stellar_metallicity_dex":24747480.3614302,
   "stellar_metallicity_upper_unc":8425957.1509072,
   "stellar_metallicity_lower_unc":144413.33
  },
  "stellar_radius":{
   "stellar_radius_solar_raddi":64023331965638.9,
   "stellar_radius_upper_unc_solar_raddi":5374091842.27,
   "stellar_radius_lower_unc_solar_raddi":1163923.158
  },
  "stellar_mass":{
   "stellar_mass_solar_mass":8.7978166256364,
   "stellar_mass_upper_unc_solar_mass":311192844078.99,
   "stellar_mass_lower_unc_solar_mass":9452247.2
  },
  "stellar_age":{
   "stellar_age_gyr":20412771.60197,
   "stellar_age_upper_unc_gyr":6054320047.2034,
   "stellar_age_lower_unc_gyr":139036.1104745
  }
 },
 "stellar_parameter_provenance":"stellar_q9_q85",
 "kic_parameters":{
  "ra":8268930102.6,
  "dec":2684.21239911,
  "kepler_band":270081837263.0,
  "g_band":737048791.297628,
  "r_band":689125.9,
  "i_band":74612363.3139,
  "z_band":28587724575.9,
  "j_band":5798.2454911826,
  "h_band":5.341102048,
  "k_band":68061377.2250214
 }
}