{
 "identification":{
  "keipID":785301283,
  "koi_name":"K000917.05"
 },
 "exoplanet_information":{
  "kepler_name":"Kepler-429 v",
  "exoplanet_disposition":"FALSE POSITIVE",
  "vetting_status":"done",
  "date_of_last_parameter_update":"2021-02-12"
 },
 "project_disposition":{
  "disposition_using_kepler_data":"FALSE POSITIVE",
  "disposition_score":0.0,
  "not_transit_like_false_positive_flag":0,
  "stellar_eclipse_false_positive_flag":1,
  "centroid_offset_false_positive_flag":10.1211873960756,
  "ephemeris_math_indicates_contamination_false_positive_flag":0,
  "disposition_provenance":"q6_q44_dr11_tcs"
 },
 "transit_properties":{
  "orbital_period":{
   "orbital_period_days":53205.8627874,
   "orbital_period_upper_unc_days":"7.8000-e01",
   "orbital_period_lower_unc_days":"-7.8000-e01"
  },
  "transit_epoch_bkjd":{
   "transit_epoch_bkjd":715213423.163,
   "transit_epoch_upper_unc_bkjd":"8.8000-e01",
   "transit_epoch_lower_unc_bkjd":"-8.8000-e01"
  },
  "transit_epoch_bjd":{
   "transit_epoch_bjd":793991292.561,
   "transit_epoch_upper_unc_bjd":"2.2000-e04",
   "transit_epoch_lower_unc_bjd":"-2.2000-e04"
  },
  "eccentricity":{
   "eccentricity":0,
   "eccentricity_upper_unc":"1",
   "eccentricity_lower_unc":"-1"
  },
  "long_periastron":{
   "long_periastron_deg":0,
   "long_periastron_upper_unc_deg":"1",
   "long_periastron_lower_unc_deg":"-1"
  },
  "impact_parameter":{
   "impact_parameter":330201735.0,
   "impact_parameter_upper_unc":4.2,
   "impact_parameter_lower_unc":-4.2
  },
  "transit_duration":{
   "transit_duration_hrs":413029108.88235,
   "transit_duration_upper_unc_hrs":0.2,
   "transit_duration_lower_unc_hrs":-0.2
  },
  "ingress_duration":{
   "ingress_duration_hrs":2961823274.685,
   "ingress_duration_upper_unc":0.3,
   "ingress_duration_lower_unc":-0.3
  },
  "transit_depth":{
   "transit_depth_ppm":5809,
   "transit_depth_upper_unc_ppm":46,
   "transit_depth_lower_unc_ppm":-46
  },
  "planet_star_radius_ratio":{
   "planet_star_radios_ratio":1.291431,
   "planet_star_radius_ratio_upper_unc":"7.4000-e04",
   "planet_star_radius_ratio_lower_unc":"-7.4000-e04"
  },
  "fitted_stellar_density":{
   "fitted_stellar_density":381102012716.751,
   "fitted_stellar_density_upper_unc_gcm3":"6.5000-e03",
   "fitted_stellar_density_lower_unc_gcm3":"-6.5000-e03"
  },
  "planetary_fit_type":61544418763.0,
  "planetary_radius":{
   "planetary_radius_earth_radii":614.81368,
   "planetary_radius_upper_unc_earth_raddi":218389022.241063,
   "planetary_radius_lower_unc_earth_raddi":-218389022.241063
  },
  "orbit_semi_major_axis":{
   "orbit_semi_major_axis_au":8046449424997.0,
   "orbit_semi_major_axis_upper_unc_au":409199.66015,
   "orbit_semi_major_axis_lower_unc_au":-409199.66015
  },
  "inclination":{
   "inclination_deg":6342889.2,
   "inclination_upper_unc_deg":68715885.0,
   "inclination_lower_unc_deg":-68715885.0
  },
  "equilibrium_temperature":{
   "equilibrium_temperature_k":7.83815405993,
   "equilibrium_temperature_upper_unc_k":71836986503.0,
   "equilibrium_temperature_lower_unc_k":-71836986503.0
  },
  "isolotaion_flux":{
   "isolation_flux":1.845,
   "isolotaion_flux_upper_unc":2452331.9613107,
   "isolation_flux_lower_unc":-2452331.9613107
  },
  "planet_star_distance_over_star_radius":{
   "planet_star_distance_over_star_radius":362370882717281.0,
   "planet_star_distance_over_star_radius_upper":"6.8000-e05",
   "planet_star_distance_over_star_radius_lower":"-6.8000-e05"
  },
  "limb_darkening_model":"Claret(2012 P&P 947 23) ATLAS AA",
  "limb_darkening_coeff_4":3988399.271833,
  "limb_darkening_coeff_3":71245081673.3128,
  "limb_darkening_coeff_2":1943740250.99077,
  "limb_darkening_coeff_1":24919000046.0,
  "parameters_provenance":"q5_q30_koi"
 },
 "threshold_corssing_event_information":{
  "maximum_single_event_statistic":782.1,
  "maximum_multiple_event_statistic":4421548049020.0,
  "transit_signal_to_noise":17093991.95562,
  "number_of_planets":36,
  "number_of_transits":8,
  "tce_planet_number":1,
  "tce_delivery":"q5_q96_tce",
  "quarters":5495502470.4113,
  "odd_even_depth_comparision_statistic":9293.92986901128,
  "transit_model":"Mandel and Agol (2009 HbB 416 426)",
  "degress_of_freedom":5176307345673.5,
  "chi_square":751.744364046967,
  "link_to_dv_report":"https://www.lorempixel.com/1002/143",
  "link_to_dv_summary":"https://placeimg.com/289/656/any"
 },
 "stellar_paramenters":{
  "stellar_effective_temperature_k":{
   "stellar_effective_temperature_k":6336.478622,
   "stellar_effective_temperature_upper_unc_k":42217275961525.0,
   "stellar_effective_temperature_lower_unc_k":3.240766866123
  },
  "stellar_surface_gravity":{
   "stellar_surface_gravity":9448848775802.0,
   "stellar_surface_gravity_upper_unc":753812154611518.0,
   "stellar_surface_gravity_lower_unc":97.3192801724514
  },
  "stellar_metallicity":{
   "stellar_metallicity_dex":-213968157099700.0,
   "stellar_metallicity_upper_unc":-602948663.0,
   "stellar_metallicity_lower_unc":-796703.50807
  },
  "stellar_radius":{
   "stellar_radius_solar_raddi":347264211650479.0,
   "stellar_radius_upper_unc_solar_raddi":322.9661084533,
   "stellar_radius_lower_unc_solar_raddi":407.51
  },
  "stellar_mass":{
   "stellar_mass_solar_mass":306485.8,
   "stellar_mass_upper_unc_solar_mass":3224679.6,
   "stellar_mass_lower_unc_solar_mass":5700.0
  },
  "stellar_age":{
   "stellar_age_gyr":78830272.33,
   "stellar_age_upper_unc_gyr":386873203205.8,
   "stellar_age_lower_unc_gyr":714176099529.81
  }
 },
 "stellar_parameter_provenance":"stellar_q9_q29",
 "kic_parameters":{
  "ra":72001437442090.0,
  "dec":749070.1,
  "kepler_band":3169574318.9,
  "g_band":37699791.811,
  "r_band":873.85,
  "i_band":14105104.0,
  "z_band":9564061693089.26,
  "j_band":2073.5693,
  "h_band":946614977852.35,
  "k_band":90209.50439101
 }
}