{
 "identification":{
  "keipID":193340474,
  "koi_name":"K000601.02"
 },
 "exoplanet_information":{
  "kepler_name":"Kepler-751 b",
  "exoplanet_disposition":"FALSE POSITIVE",
  "vetting_status":"done",
  "date_of_last_parameter_update":"2021-08-29"
 },
 "project_disposition":{
  "disposition_using_kepler_data":"NOT DISPOSITIONED",
  "disposition_score":0.0,
  "not_transit_like_false_positive_flag":0,
  "stellar_eclipse_false_positive_flag":0,
  "centroid_offset_false_positive_flag":604831413404.582,
  "ephemeris_math_indicates_contamination_false_positive_flag":0,
  "disposition_provenance":"q4_q48_dr47_tcl"
 },
 "transit_properties":{
  "orbital_period":{
   "orbital_period_days":987657232314.16,
   "orbital_period_upper_unc_days":"2.7000-e05",
   "orbital_period_lower_unc_days":"-2.7000-e05"
  },
  "transit_epoch_bkjd":{
   "transit_epoch_bkjd":67.96176283,
   "transit_epoch_upper_unc_bkjd":"1.3000-e07",
   "transit_epoch_lower_unc_bkjd":"-1.3000-e07"
  },
  "transit_epoch_bjd":{
   "transit_epoch_bjd":64746.583211363,
   "transit_epoch_upper_unc_bjd":"2.1000-e05",
   "transit_epoch_lower_unc_bjd":"-2.1000-e05"
  },
  "eccentricity":{
   "eccentricity":0,
   "eccentricity_upper_unc":"1",
   "eccentricity_lower_unc":"-1"
  },
  "long_periastron":{
   "long_periastron_deg":0,
   "long_periastron_upper_unc_deg":"1",
   "long_periastron_lower_unc_deg":"-1"
  },
  "impact_parameter":{
   "impact_parameter":365375313713.0,
   "impact_parameter_upper_unc":0.4,
   "impact_parameter_lower_unc":-0.4
  },
  "transit_duration":{
   "transit_duration_hrs":0.45,
   "transit_duration_upper_unc_hrs":8.9,
   "transit_duration_lower_unc_hrs":-8.9
  },
  "ingress_duration":{
   "ingress_duration_hrs":829.576402735,
   "ingress_duration_upper_unc":6.8,
   "ingress_duration_lower_unc":-6.8
  },
  "transit_depth":{
   "transit_depth_ppm":6219,
   "transit_depth_upper_unc_ppm":79,
   "transit_depth_lower_unc_ppm":-79
  },
  "planet_star_radius_ratio":{
   "planet_star_radios_ratio":6878570388.0,
   "planet_star_radius_ratio_upper_unc":"1.7000-e09",
   "planet_star_radius_ratio_lower_unc":"-1.7000-e09"
  },
  "fitted_stellar_density":{
   "fitted_stellar_density":789975883137.548,
   "fitted_stellar_density_upper_unc_gcm3":"8.3000-e02",
   "fitted_stellar_density_lower_unc_gcm3":"-8.3000-e02"
  },
  "planetary_fit_type":7251058849.5,
  "planetary_radius":{
   "planetary_radius_earth_radii":34711838707442.9,
   "planetary_radius_upper_unc_earth_raddi":280523.3,
   "planetary_radius_lower_unc_earth_raddi":-280523.3
  },
  "orbit_semi_major_axis":{
   "orbit_semi_major_axis_au":342.4,
   "orbit_semi_major_axis_upper_unc_au":794551196.49443,
   "orbit_semi_major_axis_lower_unc_au":-794551196.49443
  },
  "inclination":{
   "inclination_deg":6023309957.7658,
   "inclination_upper_unc_deg":95896208.93075,
   "inclination_lower_unc_deg":-95896208.93075
  },
  "equilibrium_temperature":{
   "equilibrium_temperature_k":84763.31,
   "equilibrium_temperature_upper_unc_k":3636334084.25181,
   "equilibrium_temperature_lower_unc_k":-3636334084.25181
  },
  "isolotaion_flux":{
   "isolation_flux":36107.12,
   "isolotaion_flux_upper_unc":2061771.406,
   "isolation_flux_lower_unc":-2061771.406
  },
  "planet_star_distance_over_star_radius":{
   "planet_star_distance_over_star_radius":743847846491180.0,
   "planet_star_distance_over_star_radius_upper":"7.9000-e05",
   "planet_star_distance_over_star_radius_lower":"-7.9000-e05"
  },
  "limb_darkening_model":"Claret(2002 C&E 376 31) ATLAS SW",
  "limb_darkening_coeff_4":76.5982,
  "limb_darkening_coeff_3":17.257,
  "limb_darkening_coeff_2":1934.9592988,
  "limb_darkening_coeff_1":8333.426,
  "parameters_provenance":"q2_q89_koi"
 },
 "threshold_corssing_event_information":{
  "maximum_single_event_statistic":1734210296719.3,
  "maximum_multiple_event_statistic":6450777.6,
  "transit_signal_to_noise":356929963.38055,
  "number_of_planets":28,
  "number_of_transits":5,
  "tce_planet_number":8,
  "tce_delivery":"q4_q88_tce",
  "quarters":3195883.52,
  "odd_even_depth_comparision_statistic":957.89439,
  "transit_model":"Mandel and Agol (2003 IlN 810 598)",
  "degress_of_freedom":736246249.18279,
  "chi_square":852459250.0,
  "link_to_dv_report":"https://www.lorempixel.com/807/970",
  "link_to_dv_summary":"https://www.lorempixel.com/115/588"
 },
 "stellar_paramenters":{
  "stellar_effective_temperature_k":{
   "stellar_effective_temperature_k":7276966193.0,
   "stellar_effective_temperature_upper_unc_k":21113212.73,
   "stellar_effective_temperature_lower_unc_k":435141553818680.0
  },
  "stellar_surface_gravity":{
   "stellar_surface_gravity":79246.363,
   "stellar_surface_gravity_upper_unc":60736364591663.0,
   "stellar_surface_gravity_lower_unc":63610193214.8
  },
  "stellar_metallicity":{
   "stellar_metallicity_dex":-504.6049,
   "stellar_metallicity_upper_unc":87164.63295,
   "stellar_metallicity_lower_unc":-6780.0
  },
  "stellar_radius":{
   "stellar_radius_solar_raddi":59.68,
   "stellar_radius_upper_unc_solar_raddi":6584870.0,
   "stellar_radius_lower_unc_solar_raddi":789519.0
  },
  "stellar_mass":{
   "stellar_mass_solar_mass":29.1311722124345,
   "stellar_mass_upper_unc_solar_mass":815230832885473.0,
   "stellar_mass_lower_unc_solar_mass":57.737
  },
  "stellar_age":{
   "stellar_age_gyr":72127309120249.0,
   "stellar_age_upper_unc_gyr":231.5017722,
   "stellar_age_lower_unc_gyr":2124486.5
  }
 },
 "stellar_parameter_provenance":"stellar_q6_q71",
 "kic_parameters":{
  "ra":2327610353344.81,
  "dec":28357.2180625667,
  "kepler_band":52233848147.98,
  "g_band":1797946237376.0,
  "r_band":4.1229129,
  "i_band":43918622.90594,
  "z_band":97.0,
  "j_band":46461.7570572,
  "h_band":27804042.9086102,
  "k_band":673000543590618.0
 }
}